tf_taggers/__init__.py
tf_taggers/pos_taggers/__init__.py
tf_taggers/pos_taggers/interaction_views.py
tf_taggers/pos_taggers/library.py
tf_taggers/pos_taggers/urls.py
tf_taggers/pos_taggers/views.py
tf_taggers/pos_taggers/visualization_views.py
tf_taggers/pos_taggers/lib/__init__.py
tf_taggers/pos_taggers/lib/crf_tagger.py
tf_taggers/pos_taggers/lib/nlp4j.py
tf_taggers/pos_taggers/lib/part_of_speech_tagging.py
tf_taggers/pos_taggers/lib/tree_tagger.py
tf_taggers/pos_taggers/package_data/widgets/48897fe2-72af-45fd-ad3f-d234b81e5d9b.json
tf_taggers/pos_taggers/package_data/widgets/955a28e5-48fc-40ea-a080-10e688c34be0.json
tf_taggers/pos_taggers/package_data/widgets/982aafd8-1d71-4d37-9b91-acce96e0009f.json
tf_taggers/pos_taggers/package_data/widgets/c75f0610-4be3-4e43-8a71-d6f61c78a783.json
tf_taggers/pos_taggers/package_data/widgets/f62ca10a-b828-4bcb-bf02-97d28af69ad5.json
tf_taggers/pos_taggers/static/tf_taggers.pos_taggers/icons/treeview/nlp.png
tf_taggers/pos_taggers/static/tf_taggers.pos_taggers/icons/treeview/tag_pos_do_image.png
tf_taggers/pos_taggers/static/tf_taggers.pos_taggers/icons/treeview/tag_pos_image.png
tf_taggers/pos_taggers/static/tf_taggers.pos_taggers/icons/treeview/tag_stem_image.png
tf_taggers/pos_taggers/static/tf_taggers.pos_taggers/icons/widget/nlp.png
tf_taggers/pos_taggers/static/tf_taggers.pos_taggers/icons/widget/tag_pos_do_image.png
tf_taggers/pos_taggers/static/tf_taggers.pos_taggers/icons/widget/tag_pos_image.png
tf_taggers-0.0.8.dist-info/DESCRIPTION.rst
tf_taggers-0.0.8.dist-info/METADATA
tf_taggers-0.0.8.dist-info/RECORD
tf_taggers-0.0.8.dist-info/WHEEL
tf_taggers-0.0.8.dist-info/metadata.json
tf_taggers-0.0.8.dist-info/top_level.txt
