Metadata-Version: 2.0
Name: tf-taggers
Version: 0.0.8
Summary: TextFlows taggers module
Home-page: https://github.com/xflows/tf_taggers
Author: Matej Martinc
Author-email: matej.martinc@ijs.si
License: MIT License
Platform: UNKNOWN
Classifier: Development Status :: 2 - Pre-Alpha
Classifier: Environment :: Web Environment
Classifier: Framework :: Django
Classifier: Intended Audience :: Developers
Classifier: License :: OSI Approved :: MIT License
Classifier: Operating System :: OS Independent
Classifier: Programming Language :: Python
Classifier: Programming Language :: Python :: 2
Classifier: Topic :: Internet :: WWW/HTTP
Classifier: Topic :: Internet :: WWW/HTTP :: Dynamic Content
Classifier: Topic :: Scientific/Engineering :: Artificial Intelligence
Classifier: Topic :: Software Development :: Libraries
Requires-Dist: nltk (==3.2.1)
Requires-Dist: django-discover-runner (==1.0)
Requires-Dist: numpy
Requires-Dist: scipy
Requires-Dist: scikit-learn (==0.16.1)
Requires-Dist: docx
Requires-Dist: requests
Requires-Dist: pdfminer
Requires-Dist: python-crfsuite
